bombshell/__init__.py
bombshell/core.py
bombshell/py.typed
bombshell/resources.py
bombshell/stream.py
bombshell/wait.py
bombshell-0.4.0.dist-info/METADATA
bombshell-0.4.0.dist-info/WHEEL
bombshell-0.4.0.dist-info/licenses/LICENSE
bombshell-0.4.0.dist-info/RECORD
