Metadata-Version: 2.4
Name: bombshell
Version: 0.4.0
Summary: A library for easily running shell commands, whether standalone or piped.
Project-URL: repository, https://github.com/lilellia/bombshell
Project-URL: Bug Tracker, https://github.com/lilellia/bombshell/issues
Author-email: Lily Ellington <lilell_@outlook.com>
License-File: LICENSE
Keywords: bash,command,command-line,pipe,shell,subprocess,zsh
Classifier: Development Status :: 4 - Beta
Classifier: Intended Audience :: Developers
Classifier: License :: OSI Approved :: MIT License
Classifier: Operating System :: OS Independent
Classifier: Programming Language :: Python
Classifier: Programming Language :: Python :: 3
Classifier: Programming Language :: Python :: 3.10
Classifier: Programming Language :: Python :: 3.11
Classifier: Programming Language :: Python :: 3.12
Classifier: Programming Language :: Python :: 3.13
Classifier: Programming Language :: Python :: 3.14
Classifier: Topic :: Software Development :: Libraries
Classifier: Topic :: Software Development :: Libraries :: Python Modules
Classifier: Topic :: Utilities
Requires-Python: >=3.10
Requires-Dist: typing-extensions>=4.0; python_version < '3.11'
